flask_plots/__init__.py
flask_plots/core.py
flask_plots/templates/plots/utils.html
Flask_Plots-0.0.1.dist-info/LICENSE
Flask_Plots-0.0.1.dist-info/METADATA
Flask_Plots-0.0.1.dist-info/WHEEL
Flask_Plots-0.0.1.dist-info/top_level.txt
Flask_Plots-0.0.1.dist-info/RECORD
